telescope_sdk/__init__.py
telescope_sdk/campaign.py
telescope_sdk/common.py
telescope_sdk/company.py
telescope_sdk/company_types.py
telescope_sdk/icp.py
telescope_sdk/locations.py
telescope_sdk/person.py
telescope_sdk/prospect.py
telescope_sdk/prospect_interaction_event.py
telescope_sdk/recommendation.py
telescope_sdk/sequence.py
telescope_sdk/utils.py
telescope_sdk-0.2.47.dist-info/METADATA
telescope_sdk-0.2.47.dist-info/WHEEL
telescope_sdk-0.2.47.dist-info/RECORD
