Metadata-Version: 2.1
Name: telescope-sdk
Version: 0.2.47
Summary: Telescope Python SDK
Home-page: https://github.com/telescope-eng/telescope-python-sdk
License: Proprietary
Keywords: telescope,sdk
Author: Olivier Ramier
Author-email: olivier@gotelescope.ai
Requires-Python: >=3.8,<4.0
Classifier: License :: Other/Proprietary License
Classifier: Programming Language :: Python :: 3
Classifier: Programming Language :: Python :: 3.8
Classifier: Programming Language :: Python :: 3.9
Classifier: Programming Language :: Python :: 3.10
Classifier: Programming Language :: Python :: 3.11
Requires-Dist: flake8 (>=5.0,<6.0)
Requires-Dist: pycountry (>=22.3.5,<23.0.0)
Requires-Dist: pydantic (>=2.9.2,<3.0.0)
Project-URL: Bug Tracker, https://github.com/telescope-eng/telescope-python-sdk/issues
Project-URL: Repository, https://github.com/telescope-eng/telescope-python-sdk
